with_cloudflared/__init__.py
with_cloudflared/cloudflared.py
with_cloudflared/config.py
with_cloudflared/utils.py
with_cloudflared-0.1.0.dist-info/METADATA
with_cloudflared-0.1.0.dist-info/WHEEL
with_cloudflared-0.1.0.dist-info/RECORD
