Metadata-Version: 2.1
Name: with-cloudflared
Version: 0.1.0
Summary: Context manger for Cloudflared
Author-email: Wytamma Wirth <wytamma.wirth@me.com>
Requires-Python: >=3.8
